networking_lagopus/__init__.py
networking_lagopus/_i18n.py
networking_lagopus/agent/__init__.py
networking_lagopus/agent/interface.py
networking_lagopus/agent/lagopus_lib.py
networking_lagopus/agent/lagosh.py
networking_lagopus/agent/rpc.py
networking_lagopus/cmd/__init__.py
networking_lagopus/cmd/eventlet/__init__.py
networking_lagopus/cmd/eventlet/lagopus_agent.py
networking_lagopus/common/__init__.py
networking_lagopus/common/config.py
networking_lagopus/ml2/__init__.py
networking_lagopus/ml2/agent/__init__.py
networking_lagopus/ml2/agent/lagopus_agent.py
networking_lagopus/ml2/agent/lagopus_ryuapp.py
networking_lagopus/ml2/agent/main.py
networking_lagopus/ml2/mech_driver/__init__.py
networking_lagopus/ml2/mech_driver/mech_lagopus.py
networking_lagopus/tests/__init__.py
networking_lagopus/tests/base.py
networking_lagopus/tests/test_networking_lagopus.py
networking_lagopus-1.0.0.data/data/etc/neutron/rootwrap.d/lagopus.filters
networking_lagopus-1.0.0.dist-info/DESCRIPTION.rst
networking_lagopus-1.0.0.dist-info/METADATA
networking_lagopus-1.0.0.dist-info/RECORD
networking_lagopus-1.0.0.dist-info/WHEEL
networking_lagopus-1.0.0.dist-info/entry_points.txt
networking_lagopus-1.0.0.dist-info/metadata.json
networking_lagopus-1.0.0.dist-info/pbr.json
networking_lagopus-1.0.0.dist-info/top_level.txt
